{
    "$schema": "https://json-schema.org/draft/2020-12/schema",
    "title": "ColumnTable",
    "allOf": [
        {
            "$ref": "./data.schema.json"
        },
        {
            "type": "object",
            "properties": {
                "dataType": {
                    "type": "string"
                },
                "column": {
                    "type": "string"
                },
                "sample": {
                    "type": "array",
                    "items": {
                        "type": "string"
                    }
                }
            }
        }
    ]
}
